Metadata-Version: 2.4
Name: llama-index-readers-whatsapp
Version: 0.4.1
Summary: llama-index readers whatsapp integration
Author-email: Your Name <you@example.com>
Maintainer: batmanscode
License-Expression: MIT
License-File: LICENSE
Keywords: chat,whatsapp
Requires-Python: <4.0,>=3.9
Requires-Dist: chat-miner<0.6,>=0.5.1
Requires-Dist: llama-index-core<0.15,>=0.13.0
Requires-Dist: pandas<3,>=2.2.0
